wikixml/__init__.py
wikixml/mongo.py
wikixml/structures.py
wikixml/wiki.py
wikixml-0.3.dist-info/licenses/LICENSE
wikixml-0.3.dist-info/METADATA
wikixml-0.3.dist-info/WHEEL
wikixml-0.3.dist-info/top_level.txt
wikixml-0.3.dist-info/RECORD
