Metadata-Version: 2.4
Name: wikixml
Version: 0.3
Summary: A Python Library to process wiki dumps xml.
Author: Hansimov
Project-URL: Homepage, https://github.com/Hansimov/wikixml
Project-URL: Issues, https://github.com/Hansimov/wikixml/issues
Classifier: Programming Language :: Python :: 3
Classifier: License :: OSI Approved :: MIT License
Classifier: Operating System :: OS Independent
Requires-Python: >=3.6
License-File: LICENSE
Requires-Dist: tclogger
Requires-Dist: lxml
Requires-Dist: sedb
Dynamic: license-file
